jibrel_aiohttp_swagger/__init__.py
jibrel_aiohttp_swagger/handlers.py
jibrel_aiohttp_swagger/plugin.py
jibrel_aiohttp_swagger/utils.py
jibrel_aiohttp_swagger/static/favicon-16x16.png
jibrel_aiohttp_swagger/static/favicon-32x32.png
jibrel_aiohttp_swagger/static/oauth2-redirect.html
jibrel_aiohttp_swagger/static/swagger-ui-bundle.js
jibrel_aiohttp_swagger/static/swagger-ui-bundle.js.map
jibrel_aiohttp_swagger/static/swagger-ui-standalone-preset.js
jibrel_aiohttp_swagger/static/swagger-ui-standalone-preset.js.map
jibrel_aiohttp_swagger/static/swagger-ui.css
jibrel_aiohttp_swagger/static/swagger-ui.css.map
jibrel_aiohttp_swagger/static/swagger-ui.js
jibrel_aiohttp_swagger/static/swagger-ui.js.map
jibrel_aiohttp_swagger/templates/index.html
jibrel_aiohttp_swagger-0.1.0.dist-info/METADATA
jibrel_aiohttp_swagger-0.1.0.dist-info/WHEEL
jibrel_aiohttp_swagger-0.1.0.dist-info/top_level.txt
jibrel_aiohttp_swagger-0.1.0.dist-info/RECORD
