Metadata-Version: 2.1
Name: jibrel-aiohttp-swagger
Version: 0.1.0
Summary: Plugin for aiohttp with swagger support a
Home-page: https://github.com/jibrelnetwork/jibrel-aiohttp-swagger
Author: Roman Tolkachyov
Author-email: roman.tolkachyov@jibrel.network
License: UNKNOWN
Keywords: jibrel_aiohttp_swagger
Platform: UNKNOWN
Classifier: Development Status :: 2 - Pre-Alpha
Classifier: Intended Audience :: Developers
Classifier: Natural Language :: English
Classifier: Programming Language :: Python :: 3.6
Classifier: Programming Language :: Python :: 3.7
Requires-Dist: pyyaml
Requires-Dist: aiohttp
